MANIFEST.in
README.rst
setup.py
docs/HISTORY.txt
docs/LICENSE.GPL
docs/LICENSE.txt
ftw/__init__.py
ftw.publisher.sender.egg-info/PKG-INFO
ftw.publisher.sender.egg-info/SOURCES.txt
ftw.publisher.sender.egg-info/dependency_links.txt
ftw.publisher.sender.egg-info/entry_points.txt
ftw.publisher.sender.egg-info/namespace_packages.txt
ftw.publisher.sender.egg-info/not-zip-safe
ftw.publisher.sender.egg-info/requires.txt
ftw.publisher.sender.egg-info/top_level.txt
ftw/publisher/__init__.py
ftw/publisher/sender/__init__.py
ftw/publisher/sender/adapters.py
ftw/publisher/sender/configure.zcml
ftw/publisher/sender/dependencies.zcml
ftw/publisher/sender/eventhandlers.py
ftw/publisher/sender/events.py
ftw/publisher/sender/extractor.py
ftw/publisher/sender/hooks.py
ftw/publisher/sender/interfaces.py
ftw/publisher/sender/lawgiver.zcml
ftw/publisher/sender/meta.py
ftw/publisher/sender/meta.zcml
ftw/publisher/sender/nojobs.py
ftw/publisher/sender/permissions.zcml
ftw/publisher/sender/persistence.py
ftw/publisher/sender/profiles.zcml
ftw/publisher/sender/simplelayout.py
ftw/publisher/sender/testing.py
ftw/publisher/sender/utils.py
ftw/publisher/sender/FormGen/__init__.py
ftw/publisher/sender/FormGen/configure.zcml
ftw/publisher/sender/FormGen/saveDataAdapter.py
ftw/publisher/sender/browser/__init__.py
ftw/publisher/sender/browser/addRealm.pt
ftw/publisher/sender/browser/blacklist.py
ftw/publisher/sender/browser/blacklist_listing.pt
ftw/publisher/sender/browser/configlet.py
ftw/publisher/sender/browser/configure.zcml
ftw/publisher/sender/browser/editRealm.pt
ftw/publisher/sender/browser/exectued_list_actions.pt
ftw/publisher/sender/browser/executeJobs.pt
ftw/publisher/sender/browser/executed_job_details.pt
ftw/publisher/sender/browser/interfaces.py
ftw/publisher/sender/browser/listJobs.pt
ftw/publisher/sender/browser/list_executed_jobs.pt
ftw/publisher/sender/browser/publisherConfig.pt
ftw/publisher/sender/browser/views.py
ftw/publisher/sender/browser/resources/publisher.gif
ftw/publisher/sender/easyform/__init__.py
ftw/publisher/sender/easyform/actions.py
ftw/publisher/sender/easyform/configure.zcml
ftw/publisher/sender/locales/ftw.publisher.sender.pot
ftw/publisher/sender/locales/de/LC_MESSAGES/ftw.publisher.sender.po
ftw/publisher/sender/notifier/__init__.py
ftw/publisher/sender/notifier/statusmessage.py
