Metadata-Version: 2.1
Name: ftw.publisher.sender
Version: 2.14.0
Summary: Staging and publishing addon for Plone contents.
Home-page: https://github.com/4teamwork/ftw.publisher.sender
Author: 4teamwork AG
Author-email: mailto:info@4teamwork.ch
Maintainer: Jonas Baumann
License: GPL2
Keywords: publisher sender
Platform: UNKNOWN
Classifier: Framework :: Plone
Classifier: Framework :: Plone :: 4.3
Classifier: Framework :: Plone :: 5.1
Classifier: Programming Language :: Python
Classifier: Topic :: Software Development :: Libraries :: Python Modules
Provides-Extra: development
Provides-Extra: tests_plone4
Provides-Extra: PloneFormGen
Provides-Extra: taskqueue
Provides-Extra: tests
